verilog/rtl/stream_cipher/data_router.sv
module data_router (
    /*
    input logic clk,
    nrst,  //clock and negative-edge reset
    //other signals here
    */

    // Inputs received from reader
    input logic [7:0] input_byte_pulsed,
    input logic is_key_pulsed,
    input logic input_pulse,

    // Signals sent to the key storage
    output logic [7:0] key_byte,
    output logic key_byte_pulse,

    // Signals sent to the encryption block
    output logic [7:0] byte_pulsed,
    output logic byte_pulse

);
  always_comb begin
    // First, ensure that pulses are default to low
    key_byte_pulse = 1'b0;
    byte_pulse = 1'b0;

    // Ensure that the outputs are default to low
    key_byte = 8'b0;
    byte_pulsed = 8'b0;

    // Direct the data to the correct module when data is received
    if (input_pulse) begin
      if (is_key_pulsed) begin
        key_byte = input_byte_pulsed;
        key_byte_pulse = 1'b1;
      end else begin
        byte_pulsed = input_byte_pulsed;
        byte_pulse  = 1'b1;
      end
    end
  end
endmodule

verilog/dv/stream_cipher/data_router_tb.sv
// $Id: $
// File name:   data_router_tb.sv
// Created:     03/02/2026
// Author:      Rajin Braynard
// Description: Test bench for the data_router module

`timescale 1ns / 10ps

module data_router_tb ();

  // Define local parameters used by the test bench
  localparam CLK_PERIOD = 10;

  // Declare DUT portmap signals
  logic tb_clk;
  logic tb_nrst;
  // etc...
  // Inputs received from reader
  logic [7:0] input_byte_pulsed;
  logic is_key_pulsed;
  logic input_pulse;

  // Signals sent to the key storage
  logic [7:0] key_byte;
  logic key_byte_pulse;

  // Signals sent to the encryption block
  logic [7:0] byte_pulsed;
  logic byte_pulse;

  // Declare test bench signals
  integer tb_test_num;
  integer tb_passed;
  string tb_test_case;

  // Task for standard DUT reset procedure
  task reset_dut;
    begin
      // Activate the reset
      tb_nrst = 1'b0;
      @(posedge tb_clk);
      @(posedge tb_clk);
      @(negedge tb_clk);
      // deactivate reset
      tb_nrst = 1'b1;
      @(negedge tb_clk);
      @(negedge tb_clk);
    end
  endtask

  // Add more tasks as needed
  always begin
    #(CLK_PERIOD / 2.0);
    tb_clk++;
  end

  // Signal dump
  initial begin
    $dumpfile("support/waves/stream_cipher/data_router.vcd");
    $dumpvars;
  end

  // DUT Port map
  data_router DUT (.*);

  // Test bench main process
  initial begin
    // Initialize all of the test inputs here
    // etc...
    tb_clk = 0;
    tb_nrst = 1;

    // ************************************************************************
    // Test Case 1: Power-on Reset of the DUT
    // ************************************************************************
    tb_test_case = "Power on Reset";
    tb_test_num = 1;

    reset_dut();

    // ************************************************************************
    // Test Case 2: Routing to Key Stoage
    // ************************************************************************
    tb_test_case = "Routing tot Key Storage";
    tb_test_num = 2;

    input_byte_pulsed = 8'b10101010;
    is_key_pulsed = 1'b1;
    input_pulse = 1'b0;
    @(posedge tb_clk);
    input_pulse = 1'b1;
    @(posedge tb_clk);
    input_pulse = 1'b0;
    repeat (3) @(posedge tb_clk);

    // ************************************************************************
    // Test Case 3: Routing to Encryption Block
    // ************************************************************************
    tb_test_case = "Routing to Encryption Block";
    tb_test_num = 3;

    input_byte_pulsed = 8'b10101010;
    is_key_pulsed = 1'b0;
    input_pulse = 1'b0;
    @(posedge tb_clk);
    input_pulse = 1'b1;
    @(posedge tb_clk);
    repeat (3) @(posedge tb_clk);

    // ************************************************************************
    // Test Case 4: Alternating a Route
    // ************************************************************************
    tb_test_case = "Alternating a Route";
    tb_test_num = 4;

    input_byte_pulsed = 8'b10011001;
    is_key_pulsed = 1'b1;
    input_pulse = 1'b0;
    @(posedge tb_clk);
    input_pulse = 1'b1;
    @(posedge tb_clk);
    is_key_pulsed = 1'b0;
    @(posedge tb_clk);
    input_pulse = 1'b0;
    repeat (3) @(posedge tb_clk);

    $display("\nTest cases passed: %1d/%1d\n", tb_passed, tb_test_num);
    $finish;

  end

endmodule

support/waves/stream_cipher/data_router.vcd
$date
	Mon Mar  2 19:23:39 2026
$end
$version
	Icarus Verilog
$end
$timescale
	10ps
$end
$scope module data_router_tb $end
$var wire 1 ! key_byte_pulse $end
$var wire 8 " key_byte [7:0] $end
$var wire 8 # byte_pulsed [7:0] $end
$var wire 1 $ byte_pulse $end
$var parameter 32 % CLK_PERIOD $end
$var reg 8 & input_byte_pulsed [7:0] $end
$var reg 1 ' input_pulse $end
$var reg 1 ( is_key_pulsed $end
$var reg 1 ) tb_clk $end
$var reg 1 * tb_nrst $end
$var integer 32 + tb_passed [31:0] $end
$var integer 32 , tb_test_num [31:0] $end
$scope module DUT $end
$var wire 8 - input_byte_pulsed [7:0] $end
$var wire 1 ' input_pulse $end
$var wire 1 ( is_key_pulsed $end
$var reg 1 $ byte_pulse $end
$var reg 8 . byte_pulsed [7:0] $end
$var reg 8 / key_byte [7:0] $end
$var reg 1 ! key_byte_pulse $end
$upscope $end
$scope task reset_dut $end
$upscope $end
$upscope $end
$enddefinitions $end
$comment Show the parameter values. $end
$dumpall
b1010 %
$end
#0
$dumpvars
b0 /
b0 .
bx -
b1 ,
bx +
0*
0)
x(
x'
bx &
0$
b0 #
b0 "
0!
$end
#500
1)
#1000
0)
#1500
1)
#2000
1*
0)
#2500
1)
#3000
0)
#3500
1)
#4000
0'
1(
b10101010 &
b10101010 -
b10 ,
0)
#4500
1!
b10101010 "
b10101010 /
1'
1)
#5000
0)
#5500
b0 "
b0 /
0!
0'
1)
#6000
0)
#6500
1)
#7000
0)
#7500
1)
#8000
0)
#8500
0(
b11 ,
1)
#9000
0)
#9500
1$
b10101010 #
b10101010 .
1'
1)
#10000
0)
#10500
1)
#11000
0)
#11500
1)
#12000
0)
#12500
1)
#13000
0)
#13500
b0 #
b0 .
0$
0'
1(
b10011001 &
b10011001 -
b100 ,
1)
#14000
0)
#14500
1!
b10011001 "
b10011001 /
1'
1)
#15000
0)
#15500
1$
b10011001 #
b10011001 .
b0 "
b0 /
0!
0(
1)
#16000
0)
#16500
b0 #
b0 .
0$
0'
1)
