verilog/rtl/stream_cipher/hash_generator.sv
// XTEA Algorithm: https://en.wikipedia.org/wiki/XTEA
// Note, the values of `v` in the document mentioned above will be computed
// using v[0] = previous v[0] (initial value is currently planned to be the
// XTEA Delta derived from the golden ratio: 32'h9e3779b9)
// v[1] = 32 bit counted value

module hash_generator #(
    parameter int HASH_ITERATIONS = 8
) (
    input logic clk,
    nrst,  //clock and negative-edge reset
    //other signals here

    input logic reset_hash,

    // Input receivd from key storage
    input logic [127:0] key_memory,

    // Input received from encryption block
    input logic request_hash_byte_pulse,

    // Signals sent to encryption block
    output logic [7:0] hash_byte_out,
    output logic hash_byte_pulse_out,
    output types_pkg::hash_generator_state_t generator_current_state_out
);
  typedef types_pkg::hash_generator_state_t hash_generator_state_t;
  typedef enum {
    IDLE,  // The starting initial state when no hash is computed
    READY,  // When the hash is computed and the marker is within the hashed bounds
    CALCULATING  // When the hash is being computed
  } computed_hash_state_t;

  // This is the amount of bytes in the hash
  localparam int HashByteCount = 64 / 8;  // 64 / 8 = 8
  // Magic number for the XTEA algorithm
  localparam int XTEADelta = 32'H9E3779B9;

  // Current hash served to the user ----
  hash_generator_state_t generator_current_state;
  assign generator_current_state_out = generator_current_state;

  hash_generator_state_t generator_next_state;

  logic hash_byte_pulse;
  logic next_hash_byte_pulse;
  assign hash_byte_pulse_out = hash_byte_pulse;

  logic [ 2:0] hash_byte_out_index;  // This is used to index for providing the correct output.
  // Hash has 64 bits (8 bytes). 8 possible states requires 3 bits. Therefore,
  // `hash_byte_index` needs 3 bits. If hash_byte_index is 3'b111, then the
  // current state is EXHAUSTED and the hash must be recomputed.
  logic [ 2:0] next_hash_byte_out_index;

  // This is the hash that is outputted
  logic [63:0] served_hash;
  logic [63:0] next_served_hash;

  assign hash_byte_out = served_hash[hash_byte_out_index*8+:8];

  // This is the number hash that is currently being served
  logic [31:0] hash_number;
  logic [31:0] next_hash_number;

  // Values used to compute the next hash ----
  computed_hash_state_t computed_hash_state;
  computed_hash_state_t next_computed_hash_state;

  logic [31:0] v0;
  logic [31:0] v1;

  logic [31:0] next_v0;
  logic [31:0] next_v1;

  // Essentially, this is the hash that is in progress of being computed
  logic [63:0] computed_hash;
  assign computed_hash = {v0, v1};

  logic [31:0] sum;
  logic [31:0] next_sum;

  localparam int IterationCountWidth = $clog2(HASH_ITERATIONS);

  logic [IterationCountWidth-1:0] iteration_count;
  logic [IterationCountWidth-1:0] next_iteration_count;

  // Total amount of hashes computed. This is assigned to the initial v0 when
  // computing next_hash
  logic [31:0] hash_computations_count;
  logic [31:0] next_hash_computations_count;

  // Start of 3-Block FSM for the hash generator

  // State setter for the hash generator
  always_ff @(posedge clk or negedge nrst) begin
    if (!nrst) begin
      generator_current_state <= '0;  // hash_generator_state_t::H_GROUND;
      hash_byte_pulse <= 0;
      hash_byte_out_index <= '0;
      served_hash <= '0;
      hash_number <= '0;

    end else begin
      generator_current_state <= generator_next_state;
      hash_byte_pulse <= next_hash_byte_pulse;
      hash_byte_out_index <= next_hash_byte_out_index;
      served_hash <= next_served_hash;
      hash_number <= next_hash_number;
    end
  end

  // State transition logic for the hash generator
  always_comb begin
    // Default values
    generator_next_state = generator_current_state;

    unique case (generator_current_state)
      types_pkg::H_GROUND: begin
        if (request_hash_byte_pulse) begin
          generator_next_state = types_pkg::H_FIRST_QUERRY;
        end
      end

      types_pkg::H_FIRST_QUERRY: begin
        if (computed_hash_state == READY) begin
          generator_next_state = types_pkg::H_QUERRIED;
        end
      end

      types_pkg::H_READY: begin
        if (request_hash_byte_pulse) begin
          generator_next_state = types_pkg::H_QUERRIED;
        end
      end

      types_pkg::H_QUERRIED: begin
        generator_next_state = types_pkg::H_PULSE_OUT;
      end

      types_pkg::H_PULSE_OUT: begin
        if (hash_byte_out_index < HashByteCount) begin
          generator_next_state = types_pkg::H_READY;

        end else begin
          generator_next_state = types_pkg::H_EXHAUSTED;
        end
      end

      types_pkg::H_EXHAUSTED: begin
        if (computed_hash_state == READY) begin
          generator_next_state = types_pkg::H_READY;
        end
      end

      default: begin
      end
    endcase

    if (reset_hash) begin
      generator_next_state = types_pkg::H_GROUND;
    end
  end

  // Logic for next_hash_byte_pulse and next_hash_byte_out_index
  always_comb begin
    next_hash_byte_pulse = 0;
    next_hash_byte_out_index = hash_byte_out_index;

    case (generator_current_state)
      types_pkg::H_QUERRIED: begin
        next_hash_byte_pulse = 1;
      end

      types_pkg::H_PULSE_OUT: begin
        // At this point, hash_byte_pulse should be 1, then by the next clock
        // cycle, it will be zero

        next_hash_byte_out_index = hash_byte_out_index + 1;
      end

      types_pkg::H_EXHAUSTED: begin
        if (computed_hash_state == READY) begin
          next_hash_byte_out_index = '0;
        end
      end

      default: begin
      end
    endcase

    if (reset_hash) begin
      next_hash_byte_out_index = '0;
    end
  end

  // Logic for next_hash and next_hash_number
  always_comb begin
    next_served_hash = served_hash;
    next_hash_number = hash_number;

    if (generator_current_state == types_pkg::H_EXHAUSTED && computed_hash_state == READY) begin
      next_served_hash = computed_hash;
      next_hash_number = hash_number + 1;
    end

    if (reset_hash) begin
      next_served_hash = '0;
      next_hash_number = '0;
    end
  end

  // Start of 3-Block FSM for the next hash

  // State transition setter for the next hash
  always_ff @(posedge clk or negedge nrst) begin
    if (!nrst) begin
      computed_hash_state <= '0;
      v0 <= '0;
      v1 <= '0;
      sum <= '0;
      iteration_count <= '0;
      hash_computations_count <= '0;

    end else begin
      computed_hash_state <= next_computed_hash_state;
      v0 <= next_v0;
      v1 <= next_v1;
      sum <= next_sum;
      iteration_count <= next_iteration_count;
      hash_computations_count <= next_hash_computations_count;
    end
  end

  // State transition logic for the next computed hash state
  always_comb begin
    // Default case
    next_computed_hash_state = computed_hash_state;

    unique case (computed_hash_state)
      IDLE: begin
        if (generator_current_state == types_pkg::H_FIRST_QUERRY) begin
          next_computed_hash_state = CALCULATING;
        end
      end

      CALCULATING: begin
        if (iteration_count >= HASH_ITERATIONS) begin
          next_computed_hash_state = READY;
        end
      end

      READY: begin
        if (hash_number >= hash_computations_count) begin
          // If the hash_number is equal to the amount of hashes computed,
          // that means we can start computing the next hash since it means
          // that the generator has already coped the computed hash to the
          // served hash. Similarily, if the hash_computations_count is more
          // than hash_number, we cannot compute the next hash since some
          // some hashes would be skipped
          next_computed_hash_state = CALCULATING;
        end
      end

      default: begin
      end
    endcase

    if (reset_hash) begin
      next_computed_hash_state = IDLE;
    end
  end

  // This block is the combinational circuit to compute a round of the XTEA
  // hash. This is the logic for next_v0, next_v1, and next_sum
  always_comb begin
    next_v0  = v0;
    next_v1  = v1;
    next_sum = sum;

    if (computed_hash_state == CALCULATING) begin
      if (iteration_count == 0) begin
        if (hash_computations_count == 0) begin
          // Initialize values for hash here for the first hash computation

          next_v0  = XTEADelta;
          next_v1  = hash_computations_count;
          next_sum = '0;

        end else begin
          // Initialize values for hash here for the rest of the hash
          // computations

          next_v0  = v0 ^ v1;
          next_v1  = hash_computations_count;
          next_sum = '0;
        end
      end

      next_v0 = v0 + ((((v1 << 4) ^ (v1 >> 5)) + v1) ^ (sum + key_memory[(sum&2'b11)*32+:32]));

      // Step 2: Update sum (XTEA updates sum between v0 and v1)
      next_sum = sum + XTEADelta;

      // Step 3: Update v1 using the NEW v0 and NEW sum
      next_v1 = v1 + (
          (((next_v0 << 4) ^ (next_v0 >> 5)) + next_v0) ^
          (next_sum + key_memory[((next_sum >> 11) & 2'b11) * 32+:32])
        );
    end

    if (reset_hash) begin
      next_v0  = '0;
      next_v1  = '0;
      next_sum = '0;
    end
  end

  // Logic for iteration_count, next_hash_computations_count
  always_comb begin
    next_iteration_count = iteration_count;
    next_hash_computations_count = hash_computations_count;

    case (computed_hash_state)
      CALCULATING: begin
        // Apply one round of the XTEA algorithm here

        // Note: this is the complement of the condition to transition from
        // CALCULATING to READY
        if (iteration_count < HASH_ITERATIONS) begin
          next_iteration_count = iteration_count + 1;

        end else begin
          next_iteration_count = '0;
          next_hash_computations_count = hash_computations_count + 1;
        end
      end

      default: begin
      end
    endcase

    if (reset_hash) begin
      next_iteration_count = '0;
      next_hash_computations_count = '0;
    end
  end

endmodule

verilog/dv/stream_cipher/hash_generator_tb.sv
// $Id: $
// File name:   hash_generator_tb.sv
// Created:     03/14/2026
// Author:      Rajin Braynard
// Description: Hash Generator Testbench

`timescale 1ns / 10ps

module hash_generator_tb ();

  // Define local parameters used by the test bench
  localparam CLK_PERIOD = 10;

  // Declare DUT portmap signals
  logic tb_clk;
  logic tb_nrst;
  // etc...
  logic reset_hash;

  // Input receivd from key storage
  logic [127:0] key_memory;

  // Input received from encryption block
  logic request_hash_byte_pulse;

  // Signals sent to encryption block
  logic [7:0] hash_byte_out;
  logic hash_byte_pulse_out;
  types_pkg::hash_generator_state_t generator_current_state_out;

  // Declare test bench signals
  integer tb_test_num;
  integer tb_passed;
  string tb_test_case;

  // Task for standard DUT reset procedure
  task reset_dut;
    begin
      // Activate the reset
      tb_nrst = 1'b0;
      @(posedge tb_clk);
      @(posedge tb_clk);
      @(negedge tb_clk);
      // deactivate reset
      tb_nrst = 1'b1;
      @(negedge tb_clk);
      @(negedge tb_clk);
    end
  endtask

  // Add more tasks as needed

  task test_request_hashed_byte();
    logic input_request_pulsed;

    begin
      tb_test_case = "Request Hashed Byte";
      tb_test_num = 2;

      input_request_pulsed = 0;
      key_memory = 'hABC;

      @(negedge tb_clk);
      request_hash_byte_pulse = 1;
      @(negedge tb_clk);
      request_hash_byte_pulse = 0;
      input_request_pulsed = 1;

      repeat (20) @(negedge tb_clk);

      reset_dut();
    end
  endtask

  // Clock generation block
  always begin
    #(CLK_PERIOD / 2.0);
    tb_clk++;
  end

  // Signal dump
  initial begin
    $dumpfile("support/waves/stream_cipher/hash_generator.vcd");
    $dumpvars;
  end

  // DUT Port map
  hash_generator DUT (
      .clk (tb_clk),
      .nrst(tb_nrst), /*add other ports*/

      // Inputs
      .reset_hash(reset_hash),
      .key_memory(key_memory),
      .request_hash_byte_pulse(request_hash_byte_pulse),

      // Outputs
      .hash_byte_out(hash_byte_out),
      .hash_byte_pulse_out(hash_byte_pulse_out),
      .generator_current_state_out(generator_current_state_out)
  );

  // Test bench main process
  initial begin
    // Initialize all of the test inputs here
    tb_clk = 0;
    tb_nrst = 1;
    // etc...

    // ************************************************************************
    // Test Case 1: Power-on Reset of the DUT
    // ************************************************************************
    tb_test_case = "Power on Reset";

    reset_dut();

    // ************************************************************************
    // Test Case 2: Request Hashed Byte
    // ************************************************************************

    test_request_hashed_byte();

    $display("\nTest cases passed: %1d/%1d\n", tb_passed, tb_test_num);
    $finish;

  end

endmodule

support/waves/stream_cipher/hash_generator.vcd
$date
	Tue Mar 17 14:08:19 2026
$end
$version
	Icarus Verilog
$end
$timescale
	10ps
$end
$scope module hash_generator_tb $end
$var wire 1 ! hash_byte_pulse_out $end
$var wire 8 " hash_byte_out [7:0] $end
$var wire 3 # generator_current_state_out [2:0] $end
$var parameter 32 $ CLK_PERIOD $end
$var reg 128 % key_memory [127:0] $end
$var reg 1 & request_hash_byte_pulse $end
$var reg 1 ' reset_hash $end
$var reg 1 ( tb_clk $end
$var reg 1 ) tb_nrst $end
$var integer 32 * tb_passed [31:0] $end
$var integer 32 + tb_test_num [31:0] $end
$scope module DUT $end
$var wire 1 ( clk $end
$var wire 3 , generator_current_state_out [2:0] $end
$var wire 1 ! hash_byte_pulse_out $end
$var wire 128 - key_memory [127:0] $end
$var wire 1 ) nrst $end
$var wire 1 & request_hash_byte_pulse $end
$var wire 1 ' reset_hash $end
$var wire 8 . hash_byte_out [7:0] $end
$var wire 64 / computed_hash [63:0] $end
$var parameter 32 0 HASH_ITERATIONS $end
$var parameter 32 1 HashByteCount $end
$var parameter 32 2 IterationCountWidth $end
$var parameter 32 3 XTEADelta $end
$var reg 2 4 computed_hash_state [1:0] $end
$var reg 3 5 generator_current_state [2:0] $end
$var reg 3 6 generator_next_state [2:0] $end
$var reg 3 7 hash_byte_out_index [2:0] $end
$var reg 1 8 hash_byte_pulse $end
$var reg 32 9 hash_computations_count [31:0] $end
$var reg 32 : hash_number [31:0] $end
$var reg 5 ; iteration_count [4:0] $end
$var reg 2 < next_computed_hash_state [1:0] $end
$var reg 3 = next_hash_byte_out_index [2:0] $end
$var reg 1 > next_hash_byte_pulse $end
$var reg 32 ? next_hash_computations_count [31:0] $end
$var reg 32 @ next_hash_number [31:0] $end
$var reg 5 A next_iteration_count [4:0] $end
$var reg 64 B next_served_hash [63:0] $end
$var reg 32 C next_sum [31:0] $end
$var reg 32 D next_v0 [31:0] $end
$var reg 32 E next_v1 [31:0] $end
$var reg 64 F served_hash [63:0] $end
$var reg 32 G sum [31:0] $end
$var reg 32 H v0 [31:0] $end
$var reg 32 I v1 [31:0] $end
$upscope $end
$scope task reset_dut $end
$upscope $end
$scope task test_request_hashed_byte $end
$var reg 1 J input_request_pulsed $end
$upscope $end
$upscope $end
$enddefinitions $end
$comment Show the parameter values. $end
$dumpall
b10011110001101110111100110111001 3
b11 2
b1000 1
b1000 0
b1010 $
$end
#0
$dumpvars
xJ
b0 I
b0 H
b0 G
b0 F
b0 E
b0 D
b0 C
b0 B
b0 A
b0 @
b0 ?
0>
b0 =
b0 <
b0 ;
b0 :
b0 9
08
b0 7
b0 6
b0 5
b0 4
b0 /
b0 .
bx -
b0 ,
bx +
bx *
0)
0(
x'
x&
bx %
b0 #
b0 "
0!
$end
#500
1(
#1000
0(
#1500
1(
#2000
1)
0(
#2500
1(
#3000
0(
#3500
1(
#4000
b101010111100 %
b101010111100 -
0J
b10 +
0(
#4500
1(
#5000
b1 6
1&
0(
#5500
b10 <
b1 #
b1 ,
b1 5
1(
#6000
1J
0&
0(
#6500
b1 A
b10011110001101111100111111101000 E
b10011110001101110111100110111001 C
b101010111100 D
b10 4
1(
#7000
0(
#7500
b10 A
b10000101101111011000010101010000 E
b111100011011101111001101110010 C
b11011111100100111010000011010 D
b1 ;
b10011110001101110111100110111001 G
b10011110001101111100111111101000 I
b10101011110010011110001101111100111111101000 /
b101010111100 H
1(
#8000
0(
#8500
b11 A
b10000100110100100000110110000 E
b11011010101001100110110100101011 C
b11110101110100000100000100100010 D
b10 ;
b111100011011101111001101110010 G
b10000101101111011000010101010000 I
b1101111110010011101000001101010000101101111011000010101010000 /
b11011111100100111010000011010 H
1(
#9000
0(
#9500
b100 A
b1001101011100001100000010001101 E
b1111000110111011110011011100100 C
b10111000111011011010100010111000 D
b11 ;
b11011010101001100110110100101011 G
b10000100110100100000110110000 I
b1111010111010000010000010010001000010000100110100100000110110000 /
b11110101110100000100000100100010 H
1(
#10000
0(
#10500
b101 A
b10100010111100010000000000001010 E
b10111000101010110000010011101 C
b10010111100110110011101111001 D
b100 ;
b1111000110111011110011011100100 G
b1001101011100001100000010001101 I
b1011100011101101101010001011100001001101011100001100000010001101 /
b10111000111011011010100010111000 H
1(
#11000
0(
#11500
b110 A
b1111111110101001101110000101 E
b10110101010011001101101001010110 C
b11101110111000010100111110110000 D
b101 ;
b10111000101010110000010011101 G
b10100010111100010000000000001010 I
b1001011110011011001110111100110100010111100010000000000001010 /
b10010111100110110011101111001 H
1(
#12000
0(
#12500
b111 A
b1111111101101111111011111111110 E
b1010011100001000101010000001111 C
b10101001011111110010000111110111 D
b110 ;
b10110101010011001101101001010110 G
b1111111110101001101110000101 I
b1110111011100001010011111011000000001111111110101001101110000101 /
b11101110111000010100111110110000 H
1(
#13000
0(
#13500
b1000 A
b1011010111101001110011011100001 E
b11110001101110111100110111001000 C
b11010101001111100000111001001001 D
b111 ;
b1010011100001000101010000001111 G
b1111111101101111111011111111110 I
b1010100101111111001000011111011101111111101101111111011111111110 /
b10101001011111110010000111110111 H
1(
#14000
0(
#14500
b1 ?
b0 A
b1 <
b1111011010000000010011001100111 E
b10001111111100110100011110000001 C
b11001110011100110111011011010101 D
b1000 ;
b11110001101110111100110111001000 G
b1011010111101001110011011100001 I
b1101010100111110000011100100100101011010111101001110011011100001 /
b11010101001111100000111001001001 H
1(
#15000
0(
#15500
b1 @
b1100111001110011011101101101010101111011010000000010011001100111 B
b11 6
b1 9
b0 ;
b10001111111100110100011110000001 G
b1111011010000000010011001100111 I
b1100111001110011011101101101010101111011010000000010011001100111 /
b11001110011100110111011011010101 H
b1 4
1(
#16000
0(
#16500
b10 <
1>
b100 6
b1 :
b1100111 "
b1100111 .
b1100111001110011011101101101010101111011010000000010011001100111 F
b11 #
b11 ,
b11 5
1(
#17000
0(
#17500
b1 A
b101110001010101100000100111010 C
b10001110011001010000011101100101 E
b10001011010111110100000100000000 D
b1 =
0>
b10 6
1!
18
b100 #
b100 ,
b100 5
b10 4
1(
#18000
0(
#18500
b10 A
b11101011100101110001010011101111 E
b11001100011000100011101011110011 C
b11101010000000011110010111101010 D
b1 ;
b101110001010101100000100111010 G
b10001110011001010000011101100101 I
b1000101101011111010000010000000010001110011001010000011101100101 /
b10001011010111110100000100000000 H
b100110 "
b100110 .
b1 7
0!
08
b10 #
b10 ,
b10 5
1(
#19000
0(
#19500
b11 A
b1101101001000001000100110110 E
b1101010100110011011010010101100 C
b1001111101010010001011110011111 D
b10 ;
b11001100011000100011101011110011 G
b11101011100101110001010011101111 I
b1110101000000001111001011110101011101011100101110001010011101111 /
b11101010000000011110010111101010 H
1(
#20000
0(
#20500
b100 A
b10111011101111001111001110011001 E
b1000110100010010111001100101 C
b11011100111100110001001000010110 D
b11 ;
b1101010100110011011010010101100 G
b1101101001000001000100110110 I
b100111110101001000101111001111100001101101001000001000100110110 /
b1001111101010010001011110011111 H
1(
#21000
0(
#21500
b101 A
b1010010001010000010101101110011 E
b10100111000010001010100000011110 C
b1001110000100100001000111010110 D
b100 ;
b1000110100010010111001100101 G
b10111011101111001111001110011001 I
b1101110011110011000100100001011010111011101111001111001110011001 /
b11011100111100110001001000010110 H
1(
#22000
0(
#22500
b110 A
b1110000001000100011000100110100 E
b1000101010000000010000111010111 C
b100011010001101001101110010110 D
b101 ;
b10100111000010001010100000011110 G
b1010010001010000010101101110011 I
b100111000010010000100011101011001010010001010000010101101110011 /
b1001110000100100001000111010110 H
1(
#23000
0(
#23500
b111 A
b10100110110010101101110111110010 E
b11100011011101111001101110010000 C
b1010111110010101010110111000000 D
b110 ;
b1000101010000000010000111010111 G
b1110000001000100011000100110100 I
b10001101000110100110111001011001110000001000100011000100110100 /
b100011010001101001101110010110 H
1(
#24000
0(
#24500
b1000 A
b100010100011100111000110110000 E
b10000001101011110001010101001001 C
b1001010110111000110111101001101 D
b111 ;
b11100011011101111001101110010000 G
b10100110110010101101110111110010 I
b101011111001010101011011100000010100110110010101101110111110010 /
b1010111110010101010110111000000 H
1(
#25000
0(
#25500
b10 ?
b0 A
b1 <
b10101010001001101110110101010101 E
b11111111001101000111100000010 C
b11000000010110011111011000001 D
b1000 ;
b10000001101011110001010101001001 G
b100010100011100111000110110000 I
b100101011011100011011110100110100100010100011100111000110110000 /
b1001010110111000110111101001101 H
1(
#26000
b0 ?
b0 C
b0 E
b0 D
b0 <
b0 @
b0 B
b0 =
b0 6
b0 9
b0 ;
b0 G
b0 I
b0 /
b0 H
b0 4
b0 :
b0 F
b0 "
b0 .
b0 7
b0 #
b0 ,
b0 5
0)
0(
#26500
1(
#27000
0(
#27500
1(
#28000
1)
0(
