verilog/rtl/stream_cipher/reader.sv
// Note: The purpose of this module is to convert the edge-sensitive 4 phase
// handshake input to a single-cycle pulse

module reader (
    input logic clk,
    nrst,  //clock and negative-edge reset

    // Data inputs (received from chip pins)
    input logic [7:0] input_byte_in,
    input logic command_in,

    // Handshake Management Inputs (received from chip pins)
    input logic input_request,

    // FSM State (received from fsm state block)
    input types_pkg::interface_state_t interface_fsm_state_in,

    // Signals sent to the command center
    output logic [7:0] input_byte_pulsed_out,  // This is the input byte that *gets pulsed*
    output logic command_pulsed_out,
    output logic pulse_out
);
  typedef types_pkg::interface_state_t interface_state_t;

  assign input_byte_pulsed_out = input_byte_in;
  assign command_pulsed_out = command_in;

  logic pulse;
  assign pulse_out = pulse;
  logic next_pulse;

  always_comb begin
    next_pulse = 0;

    if (interface_fsm_state_in == types_pkg::I_IDLE && input_request) begin
      next_pulse = 1;
    end
  end

  always_ff @(posedge clk or negedge nrst) begin
    if (!nrst) begin

    end else begin
      pulse <= next_pulse;
    end
  end
endmodule

verilog/rtl/stream_cipher/interface_fsm.sv
module interface_fsm (
    input logic clk,
    nrst,  //clock and negative-edge reset

    // Handshake signals
    input logic input_request_in, // Received from chip input
    input logic output_acknowledge_in, // Received from chip output
    // Received by the output holder block
    input types_pkg::output_holder_state_t output_holder_state_in,

    output types_pkg::interface_state_t interface_state_out
);
  typedef types_pkg::interface_state_t interface_state_t;

  interface_state_t next_interface_state;
  assign interface_state_out = interface_state;
  interface_state_t interface_state;

  always_ff @(posedge clk or negedge nrst) begin
    if (!nrst) begin
      interface_state <= types_pkg::I_IDLE;

    end else begin
      interface_state <= next_interface_state;
    end
  end

  always_comb begin
    // The default case
    next_interface_state = interface_state;

    unique case (interface_state)
      types_pkg::I_IDLE: begin
        if (input_request_in) begin
          next_interface_state = types_pkg::I_PROCESSING;
        end
      end

      types_pkg::I_PROCESSING: begin
        if (output_holder_state_in == types_pkg::O_READY) begin
          next_interface_state = types_pkg::I_DONE;
        end
      end

      types_pkg::I_DONE: begin
        if (output_acknowledge_in) begin
          next_interface_state = types_pkg::I_IDLE;
        end
      end
    endcase
  end
endmodule

verilog/dv/stream_cipher/interface_reader_tb.sv
// $Id: $
// File name:   interface_reader_tb.sv
// Created:     04/18/2026
// Author:      Gemini
// Description: Test bench for the interface_fsm and reader modules

`timescale 1ns / 10ps

module interface_reader_tb ();

  // Include package for custom types
  import types_pkg::*;

  // Define local parameters used by the test bench
  localparam CLK_PERIOD = 10;

  // Declare DUT portmap signals
  logic tb_clk;
  logic tb_nrst;

  // Signals for interface_fsm
  logic input_request_sig;
  logic output_acknowledge_sig;
  types_pkg::output_holder_state_t output_holder_state_sig;
  types_pkg::interface_state_t interface_state_sig;

  // Signals for reader
  logic [7:0] input_byte_sig;
  logic command_sig;
  logic [7:0] input_byte_pulsed_sig;
  logic command_pulsed_sig;
  logic pulse_sig;

  // Declare test bench signals
  integer tb_test_num;
  integer tb_passed;
  string tb_test_case;

  // Helper function to get string name of interface_state_t
  function string get_interface_state_name(types_pkg::interface_state_t state);
    case (state)
      types_pkg::I_IDLE: return "I_IDLE";
      types_pkg::I_PROCESSING: return "I_PROCESSING";
      types_pkg::I_DONE: return "I_DONE";
      default: return "UNKNOWN_INTERFACE_STATE";
    endcase
  endfunction

  // Helper function to get string name of output_holder_state_t
  function string get_output_holder_state_name(types_pkg::output_holder_state_t state);
    case (state)
      types_pkg::O_EMPTY: return "O_EMPTY";
      types_pkg::O_READY: return "O_READY";
      default: return "UNKNOWN_OUTPUT_HOLDER_STATE";
    endcase
  endfunction

  // Task for standard DUT reset procedure
  task reset_dut;
    begin
      // Activate the reset
      tb_nrst = 1'b0;
      @(posedge tb_clk);
      @(posedge tb_clk);
      @(negedge tb_clk);
      // deactivate reset
      tb_nrst = 1'b1;
      @(negedge tb_clk);
      @(negedge tb_clk);
    end
  endtask

  // Task to simulate a full 4-phase handshake cycle
  task automatic four_phase_handshake_cycle_subtask(input logic [7:0] data_in, input logic cmd_in);
    begin
      // 1. Assert input_request
      input_byte_sig = data_in;
      command_sig = cmd_in;
      input_request_sig = 1'b1;
      output_acknowledge_sig = 1'b0;
      output_holder_state_sig = O_EMPTY;

      @(negedge tb_clk);
      // Expect FSM to go to I_PROCESSING and reader to pulse
      if (interface_state_sig == I_PROCESSING && pulse_sig == 1'b1 &&
          input_byte_pulsed_sig == data_in && command_pulsed_sig == cmd_in) begin
        $display("  [PASS] %s: Input request processed. State: %s, Pulse: %b", tb_test_case,
                 get_interface_state_name(interface_state_sig), pulse_sig);
        tb_passed++;
      end else begin
        $display("  [FAIL] %s: Input request failed. State: %s, Pulse: %b", tb_test_case,
                 get_interface_state_name(interface_state_sig), pulse_sig);
      end

      // De-assert input_request after one cycle
      input_request_sig = 1'b0;
      @(negedge tb_clk);
      // Pulse should be de-asserted
      if (pulse_sig == 1'b0) begin
        $display("  [PASS] %s: Pulse de-asserted.", tb_test_case);
        tb_passed++;
      end else begin
        $display("  [FAIL] %s: Pulse not de-asserted.", tb_test_case);
      end

      // 2. Simulate output_holder becoming ready
      output_holder_state_sig = O_READY;
      @(negedge tb_clk);
      // Expect FSM to go to I_DONE
      if (interface_state_sig == I_DONE) begin
        $display("  [PASS] %s: Output holder ready. State: %s", tb_test_case,
                 get_interface_state_name(interface_state_sig));
        tb_passed++;
      end else begin
        $display("  [FAIL] %s: Output holder ready failed. State: %s", tb_test_case,
                 get_interface_state_name(interface_state_sig));
      end

      // 3. Assert output_acknowledge
      output_acknowledge_sig = 1'b1;
      @(negedge tb_clk);
      // Expect FSM to go back to I_IDLE
      if (interface_state_sig == I_IDLE) begin
        $display("  [PASS] %s: Output acknowledged. State: %s", tb_test_case,
                 get_interface_state_name(interface_state_sig));
        tb_passed++;
      end else begin
        $display("  [FAIL] %s: Output acknowledged failed. State: %s", tb_test_case,
                 get_interface_state_name(interface_state_sig));
      end

      // De-assert output_acknowledge
      output_acknowledge_sig = 1'b0;
      @(negedge tb_clk);
      output_holder_state_sig = O_EMPTY;  // Reset output holder state
    end
  endtask

  task automatic test_power_on_reset();
    begin
      tb_test_case = "Power on Reset";
      tb_test_num++;

      reset_dut();
      @(negedge tb_clk);
      if (interface_state_sig == I_IDLE && pulse_sig == 1'b0) begin
        $display("  [PASS] %s: Initial state is IDLE, pulse is 0.", tb_test_case);
        tb_passed++;
      end else begin
        $display("  [FAIL] %s: Initial state is %s, pulse is %b.", tb_test_case,
                 get_interface_state_name(interface_state_sig), pulse_sig);
      end
    end
  endtask

  task automatic test_single_handshake_cycle();
    begin
      tb_test_case = "Single Four-Phase Handshake Cycle";
      tb_test_num++;
      four_phase_handshake_cycle_subtask(8'hAB, 1'b1);  // Example data and command
    end
  endtask

  task automatic test_multiple_handshake_cycles();
    begin
      tb_test_case = "Multiple Four-Phase Handshake Cycles";
      tb_test_num++;
      four_phase_handshake_cycle_subtask(8'hCD, 1'b0);  // Example data and command
      four_phase_handshake_cycle_subtask(8'h12, 1'b1);  // Another example
      four_phase_handshake_cycle_subtask(8'h34, 1'b0);  // Another example
    end
  endtask

  task automatic test_input_request_without_output_ready();
    begin
      tb_test_case = "Input Request without Output Ready";
      tb_test_num++;

      input_byte_sig = 8'hEF;
      command_sig = 1'b1;
      input_request_sig = 1'b1;
      output_acknowledge_sig = 1'b0;
      output_holder_state_sig = O_EMPTY;

      @(negedge tb_clk);
      if (interface_state_sig == I_PROCESSING && pulse_sig == 1'b1) begin
        $display("  [PASS] %s: Input request processed. State: %s, Pulse: %b", tb_test_case,
                 get_interface_state_name(interface_state_sig), pulse_sig);
        tb_passed++;
      end else begin
        $display("  [FAIL] %s: Input request failed. State: %s, Pulse: %b", tb_test_case,
                 get_interface_state_name(interface_state_sig), pulse_sig);
      end

      input_request_sig = 1'b0;
      @(negedge tb_clk);
      if (pulse_sig == 1'b0) begin
        $display("  [PASS] %s: Pulse de-asserted.", tb_test_case);
        tb_passed++;
      end else begin
        $display("  [FAIL] %s: Pulse not de-asserted.", tb_test_case);
      end

      repeat (5) @(negedge tb_clk);  // Wait for some cycles, FSM should remain in PROCESSING
      if (interface_state_sig == I_PROCESSING) begin
        $display("  [PASS] %s: FSM remains in PROCESSING.", tb_test_case);
        tb_passed++;
      end else begin
        $display("  [FAIL] %s: FSM is in %s, expected PROCESSING.", tb_test_case,
                 get_interface_state_name(interface_state_sig));
      end

      // Now complete the handshake
      output_holder_state_sig = O_READY;
      @(negedge tb_clk);
      if (interface_state_sig == I_DONE) begin
        $display("  [PASS] %s: Output holder ready. State: %s", tb_test_case,
                 get_interface_state_name(interface_state_sig));
        tb_passed++;
      end else begin
        $display("  [FAIL] %s: Output holder ready failed. State: %s", tb_test_case,
                 get_interface_state_name(interface_state_sig));
      end

      output_acknowledge_sig = 1'b1;
      @(negedge tb_clk);
      if (interface_state_sig == I_IDLE) begin
        $display("  [PASS] %s: Output acknowledged. State: %s", tb_test_case,
                 get_interface_state_name(interface_state_sig));
        tb_passed++;
      end else begin
        $display("  [FAIL] %s: Output acknowledged failed. State: %s", tb_test_case,
                 get_interface_state_name(interface_state_sig));
      end

      output_acknowledge_sig  = 1'b0;
      output_holder_state_sig = O_EMPTY;
      @(negedge tb_clk);
    end
  endtask


  // Clock generation block
  always begin
    #(CLK_PERIOD / 2.0);
    tb_clk++;
  end

  // Signal dump
  initial begin
    $dumpfile("support/waves/stream_cipher/interface_reader.vcd");
    $dumpvars;
  end

  // DUT Port map - interface_fsm
  interface_fsm FSM (
      .clk(tb_clk),
      .nrst(tb_nrst),
      .input_request_in(input_request_sig),
      .output_acknowledge_in(output_acknowledge_sig),
      .output_holder_state_in(output_holder_state_sig),
      .interface_state_out(interface_state_sig)
  );

  // DUT Port map - reader
  reader READER (
      .clk(tb_clk),
      .nrst(tb_nrst),
      .input_byte_in(input_byte_sig),
      .command_in(command_sig),
      .input_request(input_request_sig),  // Connect to the same input request as FSM
      .interface_fsm_state_in(interface_state_sig),  // Connect FSM output to reader input
      .input_byte_pulsed_out(input_byte_pulsed_sig),
      .command_pulsed_out(command_pulsed_sig),
      .pulse_out(pulse_sig)
  );

  // Test bench main process
  initial begin
    // Initialize all of the test inputs here
    tb_clk = 0;
    tb_nrst = 1;
    input_request_sig = 0;
    output_acknowledge_sig = 0;
    output_holder_state_sig = O_EMPTY;
    input_byte_sig = '0;
    command_sig = '0;

    tb_test_num = 0;
    tb_passed = 0;

    test_power_on_reset();
    test_single_handshake_cycle();
    test_multiple_handshake_cycles();
    test_input_request_without_output_ready();

    $display("\nTotal Test Cases: %1d, Total Checks Passed: %1d\n", tb_test_num, tb_passed);
    $finish;

  end

endmodule

support/waves/stream_cipher/interface_reader.vcd
$date
	Mon Apr 20 18:09:05 2026
$end
$version
	Icarus Verilog
$end
$timescale
	10ps
$end
$scope module interface_reader_tb $end
$var wire 1 ! pulse_sig $end
$var wire 2 " interface_state_sig [1:0] $end
$var wire 8 # input_byte_pulsed_sig [7:0] $end
$var wire 1 $ command_pulsed_sig $end
$var parameter 32 % CLK_PERIOD $end
$var reg 1 & command_sig $end
$var reg 8 ' input_byte_sig [7:0] $end
$var reg 1 ( input_request_sig $end
$var reg 1 ) output_acknowledge_sig $end
$var reg 1 * output_holder_state_sig $end
$var reg 1 + tb_clk $end
$var reg 1 , tb_nrst $end
$var integer 32 - tb_passed [31:0] $end
$var integer 32 . tb_test_num [31:0] $end
$scope function get_interface_state_name $end
$var reg 2 / state [1:0] $end
$upscope $end
$scope function get_output_holder_state_name $end
$var reg 1 0 state $end
$upscope $end
$scope module FSM $end
$var wire 1 + clk $end
$var wire 1 ( input_request_in $end
$var wire 2 1 interface_state_out [1:0] $end
$var wire 1 , nrst $end
$var wire 1 ) output_acknowledge_in $end
$var wire 1 * output_holder_state_in $end
$var reg 2 2 interface_state [1:0] $end
$var reg 2 3 next_interface_state [1:0] $end
$upscope $end
$scope module READER $end
$var wire 1 + clk $end
$var wire 1 & command_in $end
$var wire 1 $ command_pulsed_out $end
$var wire 8 4 input_byte_in [7:0] $end
$var wire 8 5 input_byte_pulsed_out [7:0] $end
$var wire 1 ( input_request $end
$var wire 2 6 interface_fsm_state_in [1:0] $end
$var wire 1 , nrst $end
$var wire 1 ! pulse_out $end
$var reg 1 7 next_pulse $end
$var reg 1 8 pulse $end
$upscope $end
$scope task four_phase_handshake_cycle_subtask $end
$upscope $end
$scope task reset_dut $end
$upscope $end
$scope task test_input_request_without_output_ready $end
$upscope $end
$scope task test_multiple_handshake_cycles $end
$upscope $end
$scope task test_power_on_reset $end
$upscope $end
$scope task test_single_handshake_cycle $end
$upscope $end
$upscope $end
$enddefinitions $end
$comment Show the parameter values. $end
$dumpall
b1010 %
$end
#0
$dumpvars
x8
07
b0 6
b0 5
b0 4
b0 3
b0 2
b0 1
x0
bx /
b1 .
b0 -
0,
0+
0*
0)
0(
b0 '
0&
0$
b0 #
b0 "
x!
$end
#500
1+
#1000
0+
#1500
1+
#2000
1,
0+
#2500
0!
08
1+
#3000
0+
#3500
1+
#4000
0+
#4500
1+
#5000
b1 3
17
1(
1$
1&
b10101011 #
b10101011 5
b10101011 '
b10101011 4
b10 .
b1 -
0+
#5500
07
b1 "
b1 1
b1 6
b1 2
1!
18
1+
#6000
0(
b10 -
b1 /
0+
#6500
0!
08
1+
#7000
b10 3
1*
b11 -
0+
#7500
b10 "
b10 1
b10 6
b10 2
1+
#8000
b0 3
1)
b100 -
b10 /
0+
#8500
b0 "
b0 1
b0 6
b0 2
1+
#9000
0)
b101 -
b0 /
0+
#9500
1+
#10000
17
b1 3
1(
0$
0&
b11001101 #
b11001101 5
b11001101 '
b11001101 4
b11 .
0*
0+
#10500
07
1!
18
b1 "
b1 1
b1 6
b1 2
1+
#11000
0(
b110 -
b1 /
0+
#11500
0!
08
1+
#12000
b10 3
1*
b111 -
0+
#12500
b10 "
b10 1
b10 6
b10 2
1+
#13000
b0 3
1)
b1000 -
b10 /
0+
#13500
b0 "
b0 1
b0 6
b0 2
1+
#14000
0)
b1001 -
b0 /
0+
#14500
1+
#15000
17
b1 3
1(
1$
1&
b10010 #
b10010 5
b10010 '
b10010 4
0*
0+
#15500
07
b1 "
b1 1
b1 6
b1 2
1!
18
1+
#16000
0(
b1010 -
b1 /
0+
#16500
0!
08
1+
#17000
b10 3
1*
b1011 -
0+
#17500
b10 "
b10 1
b10 6
b10 2
1+
#18000
b0 3
1)
b1100 -
b10 /
0+
#18500
b0 "
b0 1
b0 6
b0 2
1+
#19000
0)
b1101 -
b0 /
0+
#19500
1+
#20000
17
b1 3
1(
0$
0&
b110100 #
b110100 5
b110100 '
b110100 4
0*
0+
#20500
07
1!
18
b1 "
b1 1
b1 6
b1 2
1+
#21000
0(
b1110 -
b1 /
0+
#21500
0!
08
1+
#22000
b10 3
1*
b1111 -
0+
#22500
b10 "
b10 1
b10 6
b10 2
1+
#23000
b0 3
1)
b10000 -
b10 /
0+
#23500
b0 "
b0 1
b0 6
b0 2
1+
#24000
0)
b10001 -
b0 /
0+
#24500
1+
#25000
17
b1 3
1(
1$
1&
b11101111 #
b11101111 5
b11101111 '
b11101111 4
b100 .
0*
0+
#25500
07
b1 "
b1 1
b1 6
b1 2
1!
18
1+
#26000
0(
b10010 -
b1 /
0+
#26500
0!
08
1+
#27000
b10011 -
0+
#27500
1+
#28000
0+
#28500
1+
#29000
0+
#29500
1+
#30000
0+
#30500
1+
#31000
0+
#31500
1+
#32000
b10 3
1*
b10100 -
0+
#32500
b10 "
b10 1
b10 6
b10 2
1+
#33000
b0 3
1)
b10101 -
b10 /
0+
#33500
b0 "
b0 1
b0 6
b0 2
1+
#34000
0*
0)
b10110 -
b0 /
0+
