verilog/rtl/stream_cipher/reader.sv
// Note: The purpose of this module is to convert the edge-sensitive 4 phase
// handshake input to a single-cycle pulse

module reader (
    input logic clk,
    nrst,  //clock and negative-edge reset

    // Data inputs (received from chip pins)
    input logic [7:0] input_byte,
    input logic is_key,
    input logic reset_hash,

    // Handshake Management Inputs (received from chip pins)
    input logic input_request,

    // FSM State (received from fsm state block)
    input types_pkg::interface_state_t fsm_state,

    // Signals sent to the data router
    output logic [7:0] input_byte_pulsed,  // This is the input byte that *gets pulsed*
    output logic is_key_pulsed,
    output logic input_byte_pulse,  // This is the pulse used to communicate the 2 outputs above

    // Signal sent to the hash generator
    output logic reset_hash_pulse
);
  typedef types_pkg::interface_state_t interface_state_t;
  always_ff @(posedge clk or negedge nrst) begin
    if (!nrst) begin
      input_byte_pulsed <= '0;
      is_key_pulsed <= 1'b0;
      input_byte_pulse <= 1'b0;
      reset_hash_pulse <= 1'b0;
    end else begin
      // First, ensure that pulses are reset to low
      input_byte_pulsed <= '0;
      is_key_pulsed <= 1'b0;

      if (fsm_state == types_pkg::I_IDLE && input_request) begin
        // Only perform one action at a time (avoid overlapping actions).
        // Different actions will have different precedences.
        // The precedence of each actions the user can perform is as follows:
        // 1. Reset Hash
        // 2. Input Byte

        // Reset Hash Case
        if (reset_hash) begin
          reset_hash_pulse <= 1'b1;
        end  // Input Byte Case

        else begin
          input_byte_pulsed <= input_byte;
          is_key_pulsed <= is_key;
          input_byte_pulse <= 1'b1;
        end
      end
    end
  end
endmodule

verilog/dv/stream_cipher/reader_tb.sv
// $Id: $
// File name:   src1_tb.sv
// Created:     03/05/2026
// Author:      Rajin Braynard
// Description: Reader Block Testbench

`timescale 1ns / 10ps

module reader_tb ();

  // Define local parameters used by the test bench
  localparam CLK_PERIOD = 10;

  // Declare DUT portmap signals
  logic tb_clk;
  logic tb_nrst;
  // etc...

  // Data inputs (received from chip pins)
  logic [7:0] input_byte;
  logic is_key;
  logic reset_hash;

  // Handshake Management Inputs (received from chip pins)
  logic input_request;

  // FSM State (received from fsm state block)
  types_pkg::interface_state_t fsm_state;

  // Signals sent to the data router
  logic [7:0] input_byte_pulsed;  // This is the input byte that *gets pulsed*
  logic is_key_pulsed;
  logic input_byte_pulse;  // This is the pulse used to communicate the 2 outputs above

  // Signal sent to the hash generator
  logic reset_hash_pulse;

  // Declare test bench signals
  integer tb_test_num;
  integer tb_passed;
  string tb_test_case;

  // Task for standard DUT reset procedure
  task reset_dut;
    begin
      // Activate the reset
      tb_nrst = 1'b0;
      @(posedge tb_clk);
      @(posedge tb_clk);
      @(negedge tb_clk);
      // deactivate reset
      tb_nrst = 1'b1;
      @(negedge tb_clk);
      @(negedge tb_clk);
    end
  endtask

  // Add more tasks as needed


  // Clock generation block
  always begin
    #(CLK_PERIOD / 2.0);
    tb_clk++;
  end

  // Signal dump
  initial begin
    $dumpfile("support/waves/stream_cipher/reader.vcd");
    $dumpvars;
  end

  // DUT Port map
  reader DUT (
      .clk (tb_clk),
      .nrst(tb_nrst), /*add other ports*/

      .input_byte(input_byte),
      .is_key(is_key),
      .reset_hash(reset_hash),

      .input_request(input_request),

      .fsm_state(fsm_state),

      .input_byte_pulsed(input_byte_pulsed),
      .is_key_pulsed(is_key_pulsed),
      .input_byte_pulse(input_byte_pulse),

      .reset_hash_pulse(reset_hash_pulse)
  );

  // Test bench main process
  initial begin
    // Initialize all of the test inputs here
    tb_clk = 0;
    tb_nrst = 1;
    // etc...

    // ************************************************************************
    // Test Case 1: Power-on Reset of the DUT
    // ************************************************************************
    tb_test_case = "Power on Reset";
    tb_test_num = 0;

    reset_dut();

    // ************************************************************************
    // Test Case 2: Providing Key Input
    // ************************************************************************
    tb_test_case = "Providing Key Input";
    tb_test_num = 1;

    @(negedge tb_clk);
    fsm_state = types_pkg::I_IDLE;
    @(negedge tb_clk);
    input_byte = 8'hA;
    @(negedge tb_clk);
    is_key = 1'b1;
    @(negedge tb_clk);
    input_request = 1'b1;
    repeat (4) @(negedge tb_clk);


    // ************************************************************************
    // Test Case 3: Provide Byte to Encrypt
    // ************************************************************************
    tb_test_case = "Provide Byte to Encrypt";
    tb_test_num = 2;

    reset_dut();

    @(negedge tb_clk);
    input_byte = 8'hB;
    @(negedge tb_clk);
    is_key = 1'b0;
    @(negedge tb_clk);
    input_request = 1'b1;
    repeat (4) @(negedge tb_clk);

    $display("\nTest cases passed: %1d/%1d\n", tb_passed, tb_test_num);
    $finish;

  end

endmodule

support/waves/stream_cipher/reader.vcd
$date
	Fri Mar  6 10:05:45 2026
$end
$version
	Icarus Verilog
$end
$timescale
	10ps
$end
$scope module reader_tb $end
$var wire 1 ! reset_hash_pulse $end
$var wire 1 " is_key_pulsed $end
$var wire 8 # input_byte_pulsed [7:0] $end
$var wire 1 $ input_byte_pulse $end
$var parameter 32 % CLK_PERIOD $end
$var reg 2 & fsm_state [1:0] $end
$var reg 8 ' input_byte [7:0] $end
$var reg 1 ( input_request $end
$var reg 1 ) is_key $end
$var reg 1 * reset_hash $end
$var reg 1 + tb_clk $end
$var reg 1 , tb_nrst $end
$var integer 32 - tb_passed [31:0] $end
$var integer 32 . tb_test_num [31:0] $end
$scope module DUT $end
$var wire 1 + clk $end
$var wire 2 / fsm_state [1:0] $end
$var wire 8 0 input_byte [7:0] $end
$var wire 1 ( input_request $end
$var wire 1 ) is_key $end
$var wire 1 , nrst $end
$var wire 1 * reset_hash $end
$var reg 1 $ input_byte_pulse $end
$var reg 8 1 input_byte_pulsed [7:0] $end
$var reg 1 " is_key_pulsed $end
$var reg 1 ! reset_hash_pulse $end
$upscope $end
$scope task reset_dut $end
$upscope $end
$upscope $end
$enddefinitions $end
$comment Show the parameter values. $end
$dumpall
b1010 %
$end
#0
$dumpvars
b0 1
bx 0
bx /
b0 .
bx -
0,
0+
x*
x)
x(
bx '
bx &
0$
b0 #
0"
0!
$end
#500
1+
#1000
0+
#1500
1+
#2000
1,
0+
#2500
1+
#3000
0+
#3500
1+
#4000
b1 .
0+
#4500
1+
#5000
b0 &
b0 /
0+
#5500
1+
#6000
b1010 '
b1010 0
0+
#6500
1+
#7000
1)
0+
#7500
1+
#8000
1(
0+
#8500
1$
1"
b1010 #
b1010 1
1+
#9000
0+
#9500
1"
b1010 #
b1010 1
1+
#10000
0+
#10500
1"
b1010 #
b1010 1
1+
#11000
0+
#11500
1"
b1010 #
b1010 1
1+
#12000
0$
0"
b0 #
b0 1
0,
b10 .
0+
#12500
1+
#13000
0+
#13500
1+
#14000
1,
0+
#14500
1$
1"
b1010 #
b1010 1
1+
#15000
0+
#15500
1"
b1010 #
b1010 1
1+
#16000
0+
#16500
1"
b1010 #
b1010 1
1+
#17000
b1011 '
b1011 0
0+
#17500
1"
b1011 #
b1011 1
1+
#18000
0)
0+
#18500
0"
b1011 #
b1011 1
1+
#19000
0+
#19500
b1011 #
b1011 1
1+
#20000
0+
#20500
b1011 #
b1011 1
1+
#21000
0+
#21500
b1011 #
b1011 1
1+
#22000
0+
#22500
b1011 #
b1011 1
1+
